gym_banana/__init__.py
gym_banana/envs/__init__.py
gym_banana/envs/banana_env.py
gym_banana-0.0.3.dist-info/METADATA
gym_banana-0.0.3.dist-info/WHEEL
gym_banana-0.0.3.dist-info/top_level.txt
gym_banana-0.0.3.dist-info/RECORD
